LICENSE
MANIFEST.in
README.md
setup.cfg
setup.py
MongoFrames.egg-info/PKG-INFO
MongoFrames.egg-info/SOURCES.txt
MongoFrames.egg-info/dependency_links.txt
MongoFrames.egg-info/requires.txt
MongoFrames.egg-info/top_level.txt
mongoframes/__init__.py
mongoframes/frames.py
mongoframes/pagination.py
mongoframes/queries.py
mongoframes/factory/__init__.py
mongoframes/factory/blueprints.py
mongoframes/factory/quotas.py
mongoframes/factory/makers/__init__.py
mongoframes/factory/makers/dates.py
mongoframes/factory/makers/images.py
mongoframes/factory/makers/numbers.py
mongoframes/factory/makers/selections.py
mongoframes/factory/makers/text.py
tests/factory/__init__.py
tests/factory/test_blueprints.py
tests/factory/test_factory.py
tests/factory/test_quotas.py
tests/factory/makers/__init__.py
tests/factory/makers/test_dates.py
tests/factory/makers/test_images.py
tests/factory/makers/test_makers.py
tests/factory/makers/test_numbers.py
tests/factory/makers/test_selections.py
tests/factory/makers/test_text.py