Metadata-Version: 2.1
Name: MongoFrames
Version: 1.2.11
Summary: A fast unobtrusive MongoDB ODM for Python
Home-page: https://github.com/GetmeUK/MongoFrames
Author: Anthony Blackshaw
Author-email: ant@getme.co.uk
Maintainer: Anthony Blackshaw
Maintainer-email: ant@getme.co.uk
License: MIT
Keywords: database mongo mongodb odm pymongo
Platform: UNKNOWN
Classifier: Development Status :: 4 - Beta
Classifier: Intended Audience :: Developers
Classifier: Topic :: Database
Classifier: License :: OSI Approved :: MIT License
Classifier: Operating System :: MacOS :: MacOS X
Classifier: Operating System :: Microsoft :: Windows
Classifier: Operating System :: POSIX
Classifier: Programming Language :: Python :: 3.4
Classifier: Programming Language :: Python :: 3.5
Provides-Extra: develop
Provides-Extra: test
